mezzanine_sync_pages/__init__.py
mezzanine_sync_pages/admin.py
mezzanine_sync_pages/apps.py
mezzanine_sync_pages/base.py
mezzanine_sync_pages/dump_pages.py
mezzanine_sync_pages/models.py
mezzanine_sync_pages/sync_pages.py
mezzanine_sync_pages/management/__init__.py
mezzanine_sync_pages/management/commands/__init__.py
mezzanine_sync_pages/management/commands/dump_pages.py
mezzanine_sync_pages/management/commands/sync_pages.py
mezzanine_sync_pages/templates/admin/mezzanine_sync_pages.html
mezzanine_sync_pages-1.0.1.dist-info/LICENSE
mezzanine_sync_pages-1.0.1.dist-info/METADATA
mezzanine_sync_pages-1.0.1.dist-info/WHEEL
mezzanine_sync_pages-1.0.1.dist-info/top_level.txt
mezzanine_sync_pages-1.0.1.dist-info/RECORD
