Metadata-Version: 2.1
Name: mezzanine-sync-pages
Version: 1.0.1
Summary: Django app to synchronize Mezzanine page content to and from files
Home-page: https://github.com/eht16/mezzanine-sync-pages/
Author: Enrico Tröger
Author-email: enrico.troeger@uvena.de
License: MIT
Project-URL: Travis CI, https://travis-ci.org/eht16/mezzanine-sync-pages/
Project-URL: Source code, https://github.com/eht16/mezzanine-sync-pages/
Keywords: django mezzanine pages synchronize
Platform: UNKNOWN
Classifier: Development Status :: 5 - Production/Stable
Classifier: Environment :: Web Environment
Classifier: Framework :: Django
Classifier: Intended Audience :: Developers
Classifier: License :: OSI Approved :: MIT License
Classifier: Operating System :: OS Independent
Classifier: Programming Language :: Python
Classifier: Programming Language :: Python :: 3
Classifier: Topic :: Internet :: WWW/HTTP
Requires-Python: >=3.5
